{
    "Africa": [
        "África do Sul",
        "Angola",
        "Argélia",
        "Benin",
        "Botsuana",
        "Burkina Faso",
        "Burundi",
        "Cabo Verde",
        "Camarões",
        "Chade",
        "Comores",
        "Congo",
        "Costa do Marfim",
        "Djibuti",
        "Egito",
        "Eritreia",
        "Essuatini",
        "Etiópia",
        "Gabão",
        "Gâmbia",
        "Gana",
        "Guiné",
        "Guiné-Bissau",
        "Guiné-Equatorial",
        "Lesoto",
        "Libéria",
        "Líbia",
        "Madagáscar",
        "Malawí",
        "Mali",
        "Marrocos",
        "Maurício",
        "Mauritânia",
        "Moçambique",
        "Namíbia",
        "Níger",
        "Nigéria",
        "Quênia",
        "República Árabe Saaraui Democrática",
        "República Centro-Africana",
        "República do Congo",
        "República Democrática do Congo",
        "Ruanda",
        "São Tomé e Príncipe",
        "Senegal",
        "Serra Leoa",
        "Seicheles",
        "Somália",
        "Sudão",
        "Sudão do Sul",
        "Uganda",
        "Tanzânia",
        "Togo",
        "Tunísia",
        "Zâmbia",
        "Zimbábue"        
    ],
    "America": [
        "Antígua e Barbuda",
        "Argentina",
        "Bahamas",
        "Barbados",
        "Belize",
        "Bolívia",
        "Brasil",
        "Canadá",
        "Chile",
        "Colômbia",
        "Costa Rica",
        "Cuba",
        "Dominica",
        "El Salvador",
        "Equador",
        "Estados Unidos",
        "Granada",
        "Guatemala",
        "Guiana",
        "Haiti",
        "Honduras",
        "Jamaica",
        "México",
        "Nicarágua",
        "Panamá",
        "Paraguai",
        "Peru",
        "República Dominicana",
        "Santa Lúcia",
        "São Cristóvão e Névis",
        "São Vicente e Granadinas",
        "Suriname",
        "Trinidad e Tobago",
        "Uruguai",
        "Venezuela"
    ],
    "Asia": [
        "Afeganistão",
        "Arábia Saudita",
        "Azerbaijão",
        "Bangladesh",
        "Bahrein",
        "Brunei",
        "Butão",
        "Camboja",
        "Catar",
        "Cazaquistão",
        "China",
        "Coreia Popular",
        "Coreia do Sul",
        "Emirados Árabes Unidos",
        "Filipinas",
        "Iêmen",
        "Índia",
        "Indonesia",
        "Irã",
        "Iraque",
        "Free Palestine",
        "Japão",
        "Jordânia",
        "Kuwait",
        "Laos",
        "Líbano",
        "Malásia",
        "Maldivas",
        "Myanmar",
        "Mongólia",
        "Nepal",
        "Omã",
        "Paquistão",
        "Quirguistão",
        "Síria",
        "Singapura",
        "Sri Lanka",
        "Tajiquistão",
        "Tailândia",
        "Timor-Leste",
        "Turquia",
        "Turcomenistão",
        "Uzbequistão",
        "Vietnã"
    ],
    "Europa": [
        "Albânia",
        "Alemanha",
        "Andorra",
        "Armênia",
        "Áustria",
        "Bélgica",
        "Bielorrússia",
        "Bósnia e Herzegóvina",
        "Bulgária",
        "Chipre",
        "Chipre do Norte",
        "Croácia",
        "Dinamarca",
        "Eslováquia",
        "Eslovênia",
        "Espanha",
        "Estônia",
        "Finlandia",
        "França",
        "Geórgia",
        "Grécia",
        "Hungria",
        "Irlanda",
        "Islandia",
        "Itália",
        "Kosovo",
        "Letônia",
        "Liechtenstein",
        "Lituânia",
        "Luxemburgo",
        "Macedônia",
        "Malta",
        "Moldávia",
        "Mônaco",
        "Montenegro",
        "Noruega",
        "Países Baixos",
        "Polõnia",
        "Portugal",
        "Reino Unido",
        "Romênia",
        "Rússia",
        "San Marino",
        "Sérvia",
        "Suécia",
        "Suíça",
        "Tchéquia",
        "Ucrânia",
        "Inglaterra",
        "País de Gales",
        "Escócia",
        "Irlanda do Norte"
    ],
    "Oceania": [
        "Austrália",
        "Fiji",
        "Ilhas Marshall",
        "Ilhas Salomão",
        "Kiribati",
        "Micronésia",
        "Nauru",
        "Nova Zelândia",
        "Palau",
        "Papua-Nova Guiné",
        "Samoa",
        "Tonga",
        "Tuvalu",
        "Vanuatu"
    ]
}